.travis.yml
AUTHORS.rst
CHANGES.rst
COPYRIGHT.rst
LICENSE.rst
MANIFEST.in
README.rst
bootstrap.py
buildout.cfg
setup.py
tox.ini
src/z3c/__init__.py
src/z3c.coverage.egg-info/PKG-INFO
src/z3c.coverage.egg-info/SOURCES.txt
src/z3c.coverage.egg-info/dependency_links.txt
src/z3c.coverage.egg-info/entry_points.txt
src/z3c.coverage.egg-info/namespace_packages.txt
src/z3c.coverage.egg-info/not-zip-safe
src/z3c.coverage.egg-info/requires.txt
src/z3c.coverage.egg-info/top_level.txt
src/z3c/coverage/README.txt
src/z3c/coverage/__init__.py
src/z3c/coverage/coveragediff.py
src/z3c/coverage/coveragediff.txt
src/z3c/coverage/coveragereport.py
src/z3c/coverage/sampleinput.pickle
src/z3c/coverage/tests.py
src/z3c/coverage/moresampleinput/z3c.coverage.__init__.cover
src/z3c/coverage/moresampleinput/z3c.coverage.coveragediff.cover
src/z3c/coverage/moresampleinput/z3c.coverage.coveragereport.cover
src/z3c/coverage/moresampleinput/z3c.coverage.fakenewmodule.cover
src/z3c/coverage/moresampleinput/z3c.coverage.faketestedmodule.cover
src/z3c/coverage/moresampleinput/z3c.coverage.tests.cover
src/z3c/coverage/sampleinput/decoy.txt
src/z3c/coverage/sampleinput/z3c.coverage.__init__.cover
src/z3c/coverage/sampleinput/z3c.coverage.coveragediff.cover
src/z3c/coverage/sampleinput/z3c.coverage.coveragereport.cover
src/z3c/coverage/sampleinput/z3c.coverage.tests.cover